furrow1k/__init__.py
furrow1k/furrow1k.py
furrow1k/questionaire.py
furrow1k-1.1.0.dist-info/LICENSE
furrow1k-1.1.0.dist-info/METADATA
furrow1k-1.1.0.dist-info/WHEEL
furrow1k-1.1.0.dist-info/entry_points.txt
furrow1k-1.1.0.dist-info/RECORD
