Metadata-Version: 2.1
Name: furrow1k
Version: 1.1.0
Summary: Help calculate percentage of salary to contribute to 401k
License: MIT
Author: Frank Cao
Requires-Python: >=3.12.2,<4.0.0
Classifier: License :: OSI Approved :: MIT License
Classifier: Programming Language :: Python :: 3
Requires-Dist: numpy (>=1.26.4,<2.0.0)
Requires-Dist: pydantic (>=2.7.1,<3.0.0)
